strands_rendercv/__init__.py
strands_rendercv/_version.py
strands_rendercv/render_cv.py
strands_rendercv-0.1.0.dist-info/licenses/LICENSE
strands_rendercv-0.1.0.dist-info/METADATA
strands_rendercv-0.1.0.dist-info/WHEEL
strands_rendercv-0.1.0.dist-info/top_level.txt
strands_rendercv-0.1.0.dist-info/RECORD
