Metadata-Version: 2.4
Name: strands-rendercv
Version: 0.1.0
Summary: Strands Agents tool for generating beautiful CVs with RenderCV
Author-email: Cagatay Cali <cagataycali@gmail.com>
Project-URL: Homepage, https://github.com/cagataycali/strands-rendercv
Project-URL: Repository, https://github.com/cagataycali/strands-rendercv
Keywords: cv,resume,strands,agents,ai,rendercv
Classifier: Development Status :: 4 - Beta
Classifier: Intended Audience :: Developers
Classifier: Programming Language :: Python :: 3
Classifier: Programming Language :: Python :: 3.10
Classifier: Programming Language :: Python :: 3.11
Classifier: Programming Language :: Python :: 3.12
Classifier: Programming Language :: Python :: 3.13
Requires-Python: >=3.10
License-File: LICENSE
Requires-Dist: strands-agents>=0.1.0
Requires-Dist: rendercv[full]>=1.14.0
Requires-Dist: ruamel.yaml>=0.18.0
Dynamic: license-file
